Metadata-Version: 2.1
Name: funmotd
Version: 1.1
Summary: TV Show and Movie Quotes MOTD for Terminal
Home-page: UNKNOWN
Author: veerendra2
License: Apache 2.0
Project-URL: Documentation, https://github.com/veerendra2/funmotd/blob/master/README.md
Project-URL: Bug Reports, https://github.com/veerendra2/funmotd/issues
Project-URL: Source Code, https://github.com/veerendra2/funmotd
Keywords: motd,funmotd,movies-quotes
Platform: UNKNOWN
Classifier: Programming Language :: Python :: 3.4
Classifier: License :: OSI Approved :: Apache Software License
Requires-Python: >=3.4
License-File: LICENSE
